{
   "storage" : [],
   "properties" : {
      "uiLevel" : 1,
      "displayTitle" : "1",
      "lastExportedAs" : null,
      "createdBy" : "3",
      "classLimiter" : null,
      "state" : "published",
      "keywords" : "",
      "newWindow" : "0",
      "synopsis" : null,
      "extraHeadTagsPacked" : null,
      "extraHeadTags" : null,
      "ownerUserId" : "3",
      "assetId" : "8E2UOnj_XPEghTj7nfVM0g",
      "url" : "style-underground/search",
      "paginateAfter" : "25",
      "searchRoot" : "68sKwDgf9cGH58-NZcU4lg",
      "isPrototype" : "0",
      "isHidden" : "1",
      "groupIdEdit" : "3",
      "styleTemplateId" : "Qk24uXao2yowR6zxbVJ0xA",
      "useContainers" : "0",
      "inheritUrlFromParent" : "0",
      "description" : null,
      "className" : "WebGUI::Asset::Wobject::Search",
      "stateChangedBy" : "3",
      "lineage" : "000001000001000056000006",
      "lastModified" : "1318394618",
      "groupIdView" : "7",
      "title" : "Search",
      "mobileStyleTemplateId" : "PBtmpl0000000000000060",
      "skipNotification" : "0",
      "assetSize" : "346",
      "status" : "approved",
      "menuTitle" : "Search",
      "isLockedBy" : null,
      "stateChanged" : "997995720",
      "revisionDate" : "1318394617",
      "isPackage" : "0",
      "usePackedHeadTags" : "0",
      "templateId" : "PBtmpl0000000000000200",
      "encryptPage" : "0",
      "tagId" : "1gBsXf6qSiWDELfXZVyFFQ",
      "isSystem" : "0",
      "isExportable" : "1",
      "revisedBy" : "3",
      "creationDate" : "1273032720",
      "parentId" : "CQp-RFA2pMh5lFSggPPPYg",
      "printableStyleTemplateId" : "PBtmpl0000000000000111"
   }
}
